notte_sdk/__init__.py
notte_sdk/actions.py
notte_sdk/agent_fallback.py
notte_sdk/client.py
notte_sdk/errors.py
notte_sdk/py.typed
notte_sdk/types.py
notte_sdk/utils.py
notte_sdk/endpoints/__init__.py
notte_sdk/endpoints/agents.py
notte_sdk/endpoints/base.py
notte_sdk/endpoints/files.py
notte_sdk/endpoints/functions.py
notte_sdk/endpoints/page.py
notte_sdk/endpoints/personas.py
notte_sdk/endpoints/profiles.py
notte_sdk/endpoints/sessions.py
notte_sdk/endpoints/vaults.py
notte_sdk/endpoints/workflows.py
notte_sdk/websockets/__init__.py
notte_sdk/websockets/base.py
notte_sdk/websockets/jupyter.py
notte_sdk-1.8.3.dist-info/METADATA
notte_sdk-1.8.3.dist-info/WHEEL
notte_sdk-1.8.3.dist-info/RECORD
