Metadata-Version: 2.4
Name: notte-sdk
Version: 1.8.3
Summary: The SDK for Notte
Author-email: Notte Team  <hello@notte.cc>
Requires-Python: >=3.11
Requires-Dist: halo>=0.0.28
Requires-Dist: notte-core==v1.8.3
Requires-Dist: websockets>=13.1
Provides-Extra: playwright
Requires-Dist: playwright~=1.55; extra == 'playwright'
